LICENSE
MANIFEST.in
README.rst
setup.cfg
setup.py
django_videofield.egg-info/PKG-INFO
django_videofield.egg-info/SOURCES.txt
django_videofield.egg-info/dependency_links.txt
django_videofield.egg-info/requires.txt
django_videofield.egg-info/top_level.txt
videofield/__init__.py
videofield/fields.py
videofield/models.py
videofield/tests.py