Metadata-Version: 1.1
Name: django-videofield
Version: 0.1.1
Summary: Support for video upload in Django models
Home-page: https://github.com/dvl/django-videofield
Author: André Luiz
Author-email: contato@xdvl.info
License: MIT
Keywords: django video model field
Platform: UNKNOWN
Classifier: Development Status :: 1 - Planning
Classifier: Environment :: Web Environment
Classifier: Framework :: Django
Classifier: Intended Audience :: Developers
Classifier: License :: OSI Approved :: MIT License
Classifier: Operating System :: OS Independent
Classifier: Programming Language :: Python :: 2.7
Classifier: Programming Language :: Python :: 3.4
Classifier: Programming Language :: Python :: 3.5
Classifier: Topic :: Multimedia :: Video
Classifier: Topic :: Software Development :: Libraries
